rvid/netseq/__init__.py
rvid/netseq/client.py
rvid/netseq/command.py
rvid/netseq/py.typed
rvid/netseq/server.py
rvid/networknumbers/__init__.py
rvid/networknumbers/client.py
rvid/networknumbers/command.py
rvid/networknumbers/py.typed
rvid/networknumbers/request.py
rvid/networknumbers/server.py
rvid/seq/__init__.py
rvid/seq/__version__.py
rvid/seq/basic.py
rvid/seq/command.py
rvid/seq/common.py
rvid/seq/py.typed
rvid/seq/threadsafe.py
rvid.seq-0.2.0.dist-info/LICENSE
rvid.seq-0.2.0.dist-info/METADATA
rvid.seq-0.2.0.dist-info/WHEEL
rvid.seq-0.2.0.dist-info/entry_points.txt
rvid.seq-0.2.0.dist-info/top_level.txt
rvid.seq-0.2.0.dist-info/RECORD
