Metadata-Version: 2.1
Name: rvid.seq
Version: 0.2.0
Summary: Admin-friendly, fixed-length, unique-enough, fast-enough, monotonic, identifiers.
Author-email: Arvid Müllern-Aspegren <kontakt@rvid.se>
Project-URL: homepage, https://rvid.se/seq
Project-URL: repository, https://hg.sr.ht/~rvid/rvid.seq
Requires-Python: >=3.6
License-File: LICENSE
Provides-Extra: dev
Requires-Dist: black ; extra == 'dev'
Requires-Dist: pytest ; extra == 'dev'
Requires-Dist: mypy[reports] ; extra == 'dev'
Requires-Dist: isort ; extra == 'dev'
Requires-Dist: pytest-cov ; extra == 'dev'
